aiodocker/__init__.py
aiodocker/channel.py
aiodocker/configs.py
aiodocker/constants.py
aiodocker/containers.py
aiodocker/docker.py
aiodocker/events.py
aiodocker/exceptions.py
aiodocker/execs.py
aiodocker/images.py
aiodocker/jsonstream.py
aiodocker/logs.py
aiodocker/multiplexed.py
aiodocker/networks.py
aiodocker/nodes.py
aiodocker/py.typed
aiodocker/secrets.py
aiodocker/services.py
aiodocker/ssh.py
aiodocker/stream.py
aiodocker/swarm.py
aiodocker/system.py
aiodocker/tasks.py
aiodocker/types.py
aiodocker/utils.py
aiodocker/volumes.py
aiodocker-0.25.0.dist-info/METADATA
aiodocker-0.25.0.dist-info/WHEEL
aiodocker-0.25.0.dist-info/licenses/LICENSE
aiodocker-0.25.0.dist-info/RECORD
